gemini_llm/__init__.py
gemini_llm/cli.py
gemini_llm/client.py
gemini_llm-0.1.5.dist-info/METADATA
gemini_llm-0.1.5.dist-info/WHEEL
gemini_llm-0.1.5.dist-info/entry_points.txt
gemini_llm-0.1.5.dist-info/top_level.txt
gemini_llm-0.1.5.dist-info/RECORD
