Metadata-Version: 2.4
Name: gemini-llm
Version: 0.1.5
Summary: Global CMD Gemini LLM
Requires-Dist: google-genai
